{"issue":{"id":806,"project":{"id":16,"name":"easySDI"},"tracker":{"id":2,"name":"Feature"},"status":{"id":1,"name":"New"},"priority":{"id":4,"name":"Normal"},"author":{"id":383,"name":"Blatti Yves"},"subject":"New stereotype : Resource Type (for HierarchyLevel and HierarchyLevelName)","description":"ISO Model imposes to fill HierarchyLevel and HierarchyLevelName if not a dataset.\r\nA stereotype could fill those information using easySDI resource type.","done_ratio":0,"custom_fields":[{"id":3,"name":"Sponsor","multiple":true,"value":[]},{"id":4,"name":"Functional impact"},{"id":5,"name":"Ergonomic impact"}],"created_on":"2014-08-19T13:07:13Z","updated_on":"2014-08-20T09:40:47Z","journals":[{"id":4014,"user":{"id":383,"name":"Blatti Yves"},"notes":"","created_on":"2014-08-20T09:40:40Z","details":[{"property":"attr","name":"assigned_to_id","new_value":"9"}]},{"id":4015,"user":{"id":383,"name":"Blatti Yves"},"notes":"","created_on":"2014-08-20T09:40:47Z","details":[{"property":"attr","name":"assigned_to_id","old_value":"9"}]}]}}