{"issue":{"id":977,"project":{"id":16,"name":"easySDI"},"tracker":{"id":3,"name":"Enhancement"},"status":{"id":10,"name":"Closed"},"priority":{"id":5,"name":"High"},"author":{"id":383,"name":"Blatti Yves"},"category":{"id":20,"name":"SHOP"},"fixed_version":{"id":176,"name":"4.3.2"},"subject":"Add number of products to process in the \"requests list\" view","description":"In v2, we listed \"products\" that needed to be processed, in v4 we chose to have orders in this view.\r\nThis is fine, but we should add a product count in this view, otherwise we can't know the \"amount of work to do\" in the list view and have to open all orders.\r\n\r\nWe propose to add the count of products (affected to the current user) to process in the \"requests list\" view.","start_date":"2015-04-07","done_ratio":100,"custom_fields":[{"id":3,"name":"Sponsor","multiple":true,"value":[]},{"id":4,"name":"Functional impact"},{"id":5,"name":"Ergonomic impact"}],"created_on":"2015-04-07T07:20:54Z","updated_on":"2015-08-06T09:32:43Z","closed_on":"2015-08-06T09:32:43Z","journals":[{"id":5211,"user":{"id":787,"name":"Villemagne J\u00e9r\u00f4me"},"notes":"","created_on":"2015-04-10T08:59:02Z","details":[{"property":"relation","name":"relates","new_value":"958"}]},{"id":5213,"user":{"id":787,"name":"Villemagne J\u00e9r\u00f4me"},"notes":"","created_on":"2015-04-10T08:59:57Z","details":[{"property":"attr","name":"status_id","old_value":"7","new_value":"9"},{"property":"attr","name":"assigned_to_id","old_value":"762","new_value":"383"}]},{"id":5837,"user":{"id":383,"name":"Blatti Yves"},"notes":"","created_on":"2015-08-03T07:57:03Z","details":[{"property":"attr","name":"status_id","old_value":"9","new_value":"2"}]},{"id":5838,"user":{"id":383,"name":"Blatti Yves"},"notes":"","created_on":"2015-08-03T07:57:11Z","details":[{"property":"attr","name":"status_id","old_value":"2","new_value":"3"},{"property":"attr","name":"done_ratio","old_value":"0","new_value":"100"}]},{"id":5858,"user":{"id":383,"name":"Blatti Yves"},"created_on":"2015-08-06T07:44:05Z","details":[{"property":"attr","name":"status_id","old_value":"3","new_value":"12"}]},{"id":5873,"user":{"id":383,"name":"Blatti Yves"},"created_on":"2015-08-06T07:44:36Z","details":[{"property":"attr","name":"assigned_to_id","old_value":"383","new_value":"787"}]},{"id":5888,"user":{"id":787,"name":"Villemagne J\u00e9r\u00f4me"},"notes":"","created_on":"2015-08-06T09:32:43Z","details":[{"property":"attr","name":"status_id","old_value":"12","new_value":"10"},{"property":"attr","name":"assigned_to_id","old_value":"787"},{"property":"attr","name":"fixed_version_id","new_value":"176"}]}]}}