{"issue":{"id":1317,"project":{"id":16,"name":"easySDI"},"tracker":{"id":1,"name":"Defect"},"status":{"id":10,"name":"Closed"},"priority":{"id":4,"name":"Normal"},"author":{"id":817,"name":"Pochet Gilles"},"assigned_to":{"id":817,"name":"Pochet Gilles"},"category":{"id":13,"name":"CONTACT"},"fixed_version":{"id":179,"name":"4.4.1"},"subject":"test email","description":"","start_date":"2016-04-18","done_ratio":50,"custom_fields":[{"id":2,"name":"Affected version","value":"179"}],"created_on":"2016-04-18T09:16:23Z","updated_on":"2016-04-20T08:50:04Z","closed_on":"2016-04-20T08:50:04Z","journals":[{"id":7602,"user":{"id":817,"name":"Pochet Gilles"},"notes":"","created_on":"2016-04-18T09:21:05Z","details":[{"property":"attr","name":"done_ratio","old_value":"0","new_value":"20"}]},{"id":7603,"user":{"id":817,"name":"Pochet Gilles"},"notes":"dewqewq","created_on":"2016-04-18T09:25:05Z","details":[{"property":"attr","name":"done_ratio","old_value":"20","new_value":"30"}]},{"id":7604,"user":{"id":817,"name":"Pochet Gilles"},"notes":"awerawewerwer","created_on":"2016-04-18T09:27:05Z","details":[]},{"id":7605,"user":{"id":817,"name":"Pochet Gilles"},"notes":"","created_on":"2016-04-18T09:52:01Z","details":[{"property":"attr","name":"done_ratio","old_value":"30","new_value":"40"}]},{"id":7606,"user":{"id":817,"name":"Pochet Gilles"},"notes":"","created_on":"2016-04-18T12:09:26Z","details":[{"property":"attr","name":"done_ratio","old_value":"40","new_value":"50"}]},{"id":7607,"user":{"id":817,"name":"Pochet Gilles"},"notes":"","created_on":"2016-04-20T08:49:42Z","details":[{"property":"attr","name":"status_id","old_value":"2","new_value":"3"}]},{"id":7608,"user":{"id":817,"name":"Pochet Gilles"},"notes":"","created_on":"2016-04-20T08:50:04Z","details":[{"property":"attr","name":"status_id","old_value":"3","new_value":"10"}]}]}}